prosperity3bt/__init__.py
prosperity3bt/__main__.py
prosperity3bt/data.py
prosperity3bt/datamodel.py
prosperity3bt/file_reader.py
prosperity3bt/models.py
prosperity3bt/open.py
prosperity3bt/parse_submission_logs.py
prosperity3bt/py.typed
prosperity3bt/runner.py
prosperity3bt/resources/__init__.py
prosperity3bt/resources/round0/__init__.py
prosperity3bt/resources/round0/prices_round_0_day_-1.csv
prosperity3bt/resources/round0/trades_round_0_day_-1_nn.csv
prosperity3bt/resources/round1/__init__.py
prosperity3bt/resources/round1/prices_round_1_day_-1.csv
prosperity3bt/resources/round1/prices_round_1_day_-2.csv
prosperity3bt/resources/round1/prices_round_1_day_0.csv
prosperity3bt/resources/round1/trades_round_1_day_-1_nn.csv
prosperity3bt/resources/round1/trades_round_1_day_-2_nn.csv
prosperity3bt/resources/round1/trades_round_1_day_0_nn.csv
prosperity3bt/resources/round2/__init__.py
prosperity3bt/resources/round2/prices_round_2_day_-1.csv
prosperity3bt/resources/round2/prices_round_2_day_0.csv
prosperity3bt/resources/round2/prices_round_2_day_1.csv
prosperity3bt/resources/round2/trades_round_2_day_-1_nn.csv
prosperity3bt/resources/round2/trades_round_2_day_0_nn.csv
prosperity3bt/resources/round2/trades_round_2_day_1_nn.csv
prosperity3bt/resources/round3/__init__.py
prosperity3bt/resources/round3/prices_round_3_day_0.csv
prosperity3bt/resources/round3/prices_round_3_day_1.csv
prosperity3bt/resources/round3/prices_round_3_day_2.csv
prosperity3bt/resources/round3/trades_round_3_day_0_nn.csv
prosperity3bt/resources/round3/trades_round_3_day_1_nn.csv
prosperity3bt/resources/round3/trades_round_3_day_2_nn.csv
prosperity3bt/resources/round4/__init__.py
prosperity3bt/resources/round4/observations_round_4_day_1.csv
prosperity3bt/resources/round4/observations_round_4_day_2.csv
prosperity3bt/resources/round4/observations_round_4_day_3.csv
prosperity3bt/resources/round4/prices_round_4_day_1.csv
prosperity3bt/resources/round4/prices_round_4_day_2.csv
prosperity3bt-0.10.0.dist-info/licenses/LICENSE
prosperity3bt-0.10.0.dist-info/METADATA
prosperity3bt-0.10.0.dist-info/WHEEL
prosperity3bt-0.10.0.dist-info/entry_points.txt
prosperity3bt-0.10.0.dist-info/top_level.txt
prosperity3bt-0.10.0.dist-info/RECORD
