Metadata-Version: 2.4
Name: prosperity3bt
Version: 0.10.0
Summary: Backtester for IMC Prosperity 3 algorithms
Author-email: Jasper van Merle <jaspervmerle@gmail.com>
License: MIT License
Project-URL: Repository, https://github.com/jmerle/imc-prosperity-3-backtester
Project-URL: Issues, https://github.com/jmerle/imc-prosperity-3-backtester/issues
Project-URL: Changelog, https://github.com/jmerle/imc-prosperity-3-backtester/releases
Keywords: imc,prosperity,backtest,backtester
Classifier: Development Status :: 4 - Beta
Classifier: Intended Audience :: Developers
Classifier: Intended Audience :: Financial and Insurance Industry
Classifier: License :: OSI Approved :: MIT License
Classifier: Programming Language :: Python :: 3
Requires-Python: >=3.9
License-File: LICENSE
Requires-Dist: ipython>=8.18.1
Requires-Dist: jsonpickle>=4.0.2
Requires-Dist: orjson>=3.10.15
Requires-Dist: tqdm>=4.67.1
Requires-Dist: typer>=0.15.2
Dynamic: license-file
